vantage6/hq/__init__.py
vantage6/hq/algo_store_communication.py
vantage6/hq/dataclass.py
vantage6/hq/db.py
vantage6/hq/default_roles.py
vantage6/hq/globals.py
vantage6/hq/permission.py
vantage6/hq/utils.py
vantage6/hq/websockets.py
vantage6/hq/wsgi.py
vantage6/hq/_data/unittest_config.yaml
vantage6/hq/cli/__init__.py
vantage6/hq/cli/hq.py
vantage6/hq/controller/__init__.py
vantage6/hq/controller/cleanup.py
vantage6/hq/model/__init__.py
vantage6/hq/model/algorithm_store.py
vantage6/hq/model/authenticatable.py
vantage6/hq/model/base.py
vantage6/hq/model/collaboration.py
vantage6/hq/model/column.py
vantage6/hq/model/dataframe.py
vantage6/hq/model/dataframe_to_be_deleted_at_node.py
vantage6/hq/model/member.py
vantage6/hq/model/node.py
vantage6/hq/model/node_config.py
vantage6/hq/model/organization.py
vantage6/hq/model/permission.py
vantage6/hq/model/role.py
vantage6/hq/model/role_rule_association.py
vantage6/hq/model/rule.py
vantage6/hq/model/run.py
vantage6/hq/model/session.py
vantage6/hq/model/study.py
vantage6/hq/model/task.py
vantage6/hq/model/task_database.py
vantage6/hq/model/task_depends_on.py
vantage6/hq/model/user.py
vantage6/hq/model/common/utils.py
vantage6/hq/resource/__init__.py
vantage6/hq/resource/algorithm_store.py
vantage6/hq/resource/blobstream.py
vantage6/hq/resource/collaboration.py
vantage6/hq/resource/dataframe.py
vantage6/hq/resource/event.py
vantage6/hq/resource/health.py
vantage6/hq/resource/node.py
vantage6/hq/resource/organization.py
vantage6/hq/resource/recover.py
vantage6/hq/resource/role.py
vantage6/hq/resource/rule.py
vantage6/hq/resource/run.py
vantage6/hq/resource/session.py
vantage6/hq/resource/stats.py
vantage6/hq/resource/study.py
vantage6/hq/resource/task.py
vantage6/hq/resource/token.py
vantage6/hq/resource/user.py
vantage6/hq/resource/version.py
vantage6/hq/resource/websocket_test.py
vantage6/hq/resource/common/input_schema.py
vantage6/hq/resource/common/output_schema.py
vantage6/hq/resource/common/task_post_base.py
vantage6_hq-5.0.0b2.dist-info/METADATA
vantage6_hq-5.0.0b2.dist-info/WHEEL
vantage6_hq-5.0.0b2.dist-info/entry_points.txt
vantage6_hq-5.0.0b2.dist-info/RECORD
