Metadata-Version: 2.4
Name: vantage6-hq
Version: 5.0.0b2
Summary: Vantage6 HQ
Author: Vantage6 Team
Maintainer-email: Frank Martin <f.martin@iknl.nl>, Bart van Beusekom <b.vanbeusekom@iknl.nl>
License: MIT
Requires-Python: >=3.13
Requires-Dist: azure-identity==1.22.0
Requires-Dist: azure-storage-blob==12.25.1
Requires-Dist: bcrypt==4.0.1
Requires-Dist: flask-jwt-extended==4.7.1
Requires-Dist: flask-principal==0.4.0
Requires-Dist: flask-restful==0.3.10
Requires-Dist: flask-socketio==5.5.1
Requires-Dist: flask==3.1.1
Requires-Dist: gevent==25.4.2
Requires-Dist: httpx==0.28.1
Requires-Dist: ipython==8.10.0
Requires-Dist: kombu==5.5.4
Requires-Dist: marshmallow==3.20.2
Requires-Dist: names-generator==0.2.0
Requires-Dist: prometheus-client==0.21.1
Requires-Dist: pyjwt==2.9.0
Requires-Dist: python-keycloak==5.5.0
Requires-Dist: requests-oauthlib==1.3.1
Requires-Dist: requests==2.32.4
Requires-Dist: schema==0.7.5
Requires-Dist: sqlalchemy==2.0.37
Requires-Dist: traitlets==5.8.1
Requires-Dist: vantage6-common==5.0.0b2
Requires-Dist: vantage6==5.0.0b2
Requires-Dist: werkzeug==3.1.4
Provides-Extra: dev
Requires-Dist: black; extra == 'dev'
Requires-Dist: coverage==7.10.2; extra == 'dev'
Requires-Dist: pre-commit; extra == 'dev'
